print_numbers/__init__.py
print_numbers/print_number.py
hookfang_test-0.0.5.dist-info/METADATA
hookfang_test-0.0.5.dist-info/WHEEL
hookfang_test-0.0.5.dist-info/top_level.txt
hookfang_test-0.0.5.dist-info/RECORD
