Metadata-Version: 2.1
Name: hookfang-test
Version: 0.0.5
Summary: Temp Package
Home-page: UNKNOWN
Author: Edwin
License: UNKNOWN
Platform: UNKNOWN
Requires-Python: >=3.6
